AUTHORS
CHANGES
COPYING
INSTALL
MANIFEST.in
README
RELEASE_PROCESS.txt
UPGRADE
setup.cfg
setup.py
bin/kforge-admin
bin/kforge-makeconfig
bin/kforge-ssh-handler
bin/kforge-test
bin/kforgevirtualenvhandlers.py
doc/old/cli_shell.txt
doc/old/faq.txt
doc/old/guide.txt
doc/old/index.html
doc/old/kforge_system_overview.txt
doc/old/plugin_system.txt
doc/old/plugin_system_diagram.txt
doc/source/admin-guide.rst
doc/source/cli_shell.rst.txt
doc/source/conf.py
doc/source/design-guide.rst
doc/source/faq.rst
doc/source/index.rst
doc/source/install-guide.rst
doc/source/introduction.rst
doc/source/plugin-guide.rst
doc/source/plugin_system_diagram.rst
doc/source/user-guide.rst
src/kforge/__init__.py
src/kforge/accesscontrol.py
src/kforge/accesscontroltest.py
src/kforge/apachetest.py
src/kforge/applicationtest.py
src/kforge/builder.py
src/kforge/commandtest.py
src/kforge/dictionary.py
src/kforge/dictionarytest.py
src/kforge/dictionarywords.py
src/kforge/domtest.py
src/kforge/exceptions.py
src/kforge/filesystem.py
src/kforge/filesystemtest.py
src/kforge/handlerstest.py
src/kforge/ioc.py
src/kforge/kuitest.py
src/kforge/migrate.py
src/kforge/migratetest.py
src/kforge/plugintest.py
src/kforge/regexps.py
src/kforge/registry.py
src/kforge/soleInstance.py
src/kforge/testrunner.py
src/kforge/testunit.py
src/kforge/unittesttest.py
src/kforge/url.py
src/kforge/urltest.py
src/kforge/utilstest.py
src/kforge.egg-info/PKG-INFO
src/kforge.egg-info/SOURCES.txt
src/kforge.egg-info/dependency_links.txt
src/kforge.egg-info/not-zip-safe
src/kforge.egg-info/requires.txt
src/kforge.egg-info/top_level.txt
src/kforge/apache/__init__.py
src/kforge/apache/config.py
src/kforge/apache/configtest.py
src/kforge/apache/urlpermission.py
src/kforge/apache/urlpermissiontest.py
src/kforge/application/__init__.py
src/kforge/cli/__init__.py
src/kforge/cli/admin.py
src/kforge/cli/admintest.py
src/kforge/cli/data.py
src/kforge/cli/datatest.py
src/kforge/cli/makeconfig.py
src/kforge/cli/ssh.py
src/kforge/cli/test.py
src/kforge/command/__init__.py
src/kforge/command/backup.py
src/kforge/command/backuptest.py
src/kforge/command/emailjoinrequest.py
src/kforge/command/emailjoinrequesttest.py
