Metadata-Version: 1.1
Name: kforge
Version: 0.20
Summary: Enterprise architecture for project hosting
Home-page: http://www.kforgeproject.com/
Author: Appropriate Software Foundation and Open Knowledge Foundation
Author-email: john.bywater@appropriatesoftware.net
License: AGPL
Platform: UNKNOWN
Classifier: Development Status :: 5 - Production/Stable
Classifier: Environment :: Console
Classifier: Environment :: Web Environment
Classifier: Intended Audience :: Developers
Classifier: License :: OSI Approved :: GNU Affero General Public License v3
Classifier: Operating System :: OS Independent
Classifier: Programming Language :: Python
Classifier: Topic :: Software Development :: Libraries :: Python Modules
